Mv1ToolBox/__init__.py
Mv1ToolBox-0.1.dist-info/LICENSE.TXT
Mv1ToolBox-0.1.dist-info/METADATA
Mv1ToolBox-0.1.dist-info/WHEEL
Mv1ToolBox-0.1.dist-info/top_level.txt
Mv1ToolBox-0.1.dist-info/RECORD
