Metadata-Version: 2.1
Name: Mv1ToolBox
Version: 0.1
Summary: This is a very basic library
Home-page: UNKNOWN
Author: Anand Babu
Author-email: ababu.nano@gmail.com
License: UNKNOWN
Platform: UNKNOWN
Classifier: Programming Language :: Python :: 3
Classifier: License :: OSI Approved :: MIT License
Classifier: Operating System :: OS Independent
License-File: LICENSE.TXT
